LICENSE
MANIFEST.in
README.md
setup.py
bdei/BDEI.cpp
bdei/BDEI.hpp
bdei/pool.hpp
bdei/queue.hpp
bdei/semaphore.hpp
pybdei/__init__.py
pybdei/_pybdei.cpp
pybdei/_pybdei.hpp
pybdei/_python.hpp
pybdei/inference.py
pybdei/loglikelihood.py
pybdei/u_calculator.py
pybdei.egg-info/PKG-INFO
pybdei.egg-info/SOURCES.txt
pybdei.egg-info/dependency_links.txt
pybdei.egg-info/entry_points.txt
pybdei.egg-info/requires.txt
pybdei.egg-info/top_level.txt