Metadata-Version: 2.1
Name: pybdei
Version: 0.12
Summary: Fast and accurate epidemiological parameter estimation from phylogenetic trees with the Birth-Death Exposed-Infectious (BDEI) model.
Home-page: https://github.com/evolbioinfo/BDEI
Download-URL: https://github.com/evolbioinfo/BDEI
Author: Frédéric Heicht
Author-email: frederic.hecht@sorbonne-universite.fr
Maintainer: Anna Zhukova
Maintainer-email: anna.zhukova@pasteur.fr
Keywords: BDEI,phylodynamics,epidemiological parameters
Classifier: Development Status :: 4 - Beta
Classifier: Environment :: Console
Classifier: Topic :: Scientific/Engineering :: Bio-Informatics
Classifier: Topic :: Software Development :: Libraries :: Python Modules
Classifier: Programming Language :: Python :: 3
Classifier: Programming Language :: Python :: 3.9
Classifier: Programming Language :: Python :: 3.10
Classifier: Programming Language :: Python :: 3 :: Only
License-File: LICENSE
